{"august": 1, "tage": 1, "spur": 1, "trag\u00f6die": 2, "stoff": 2, "regierung": 1, "betr\u00fcger": 1, "prinzen": 1, "gr\u00fcnde": 1, "parthie": 1, "thron": 1, "prinzessin": 1, "hauses": 1, "betrug": 2, "warbeck": 1, "b\u00fchne": 1, "f\u00fcrst": 1, "hof": 1, "rolle": 3, "zeitlang": 1, "unternehmung": 1, "geschichte": 2, "situation": 2, "figuren": 1, "herzogin": 1, "grundlage": 2, "handlung": 1, "freiheit": 1, "zeit": 1, "personen": 1, "gattung": 1, "stoffen": 1, "vortheile": 1, "dramas": 1, "behandlung": 1, "stoffs": 1, "gegentheil": 1, "kom\u00f6diendichter": 1, "contrast": 1, "incompetenz": 1, "l\u00e4cherliche": 1, "werkzeug": 1, "gesch\u00f6pf": 1, "k\u00e4mpfe": 1, "platz": 1, "natur": 1, "katastrophe": 1, "anh\u00e4nger": 1, "besch\u00fctzer": 1, "feinde": 1, "gutes": 1, "fabel": 1, "mitte": 1, "st\u00fccks": 1, "stunden": 1, "almanach": 1, "aussichten": 1, "kupfer": 1, "hoffnung": 1, "g\u00fcte": 1, "manier": 1, "zeichnung": 1, "bemerkung": 1, "gedicht": 1, "gedanken": 1, "umstand": 1, "gedichten": 1, "raum": 1, "sachen": 1, "akt": 1, "sache": 1, "leben": 1, "frau": 1}