{"brief": 3, "tage": 2, "bruder": 1, "ende": 1, "bl\u00e4tter": 1, "h\u00e4ndler": 1, "damen": 1, "blumen": 1, "bord\u00fcren": 1, "post": 1, "datum": 1, "ankunft": 2, "f\u00e4llen": 1, "sache": 1, "posten": 1, "versendung": 1, "halstuch": 1, "freude": 1, "dingen": 1, "rede": 1, "eger": 1, "wasser": 1, "flaschen": 1, "k\u00e4stchen": 1, "brunnen": 1, "thaler": 1, "papier": 1, "transport": 1, "wetter": 2, "sonne": 1, "g\u00e4ste": 1, "monat": 1, "quartier": 1, "lage": 1, "frau": 1, "madame": 1, "zeit": 3, "jahren": 1, "tisch": 1, "wein": 1, "fr\u00fchst\u00fcck": 1, "ausgaben": 1, "thalern": 1, "geld": 1, "woche": 1, "kaiserin": 2, "zuflu\u00df": 1, "menschen": 1, "tag": 1, "shawl": 1, "t\u00fcchelchen": 1, "seiten": 1, "zierat": 1, "dutzend": 1, "exemplare": 1, "gedichts": 1, "karlsbader": 1, "jugend": 1, "stadt": 1, "tagen": 1, "herr": 1}