{"thal": 1, "wei\u00dferitz": 1, "gelegenheit": 2, "lage": 2, "puncte": 1, "th\u00e4ler": 2, "ruine": 1, "schlosses": 1, "anh\u00f6he": 1, "ort": 2, "bekanntschaft": 1, "herrn": 7, "anstalt": 2, "leute": 1, "forstwesen": 1, "erziehungsinstitute": 1, "tochter": 2, "enkel": 1, "eckchen": 1, "welt": 1, "zeit": 4, "hause": 3, "frau": 4, "grotthu\u00df": 1, "beinen": 1, "ankunft": 2, "potentaten": 1, "br\u00fccke": 3, "k\u00fcgelgen": 1, "neustadt": 2, "reuterei": 1, "art": 1, "kibitken": 1, "reisewagen": 1, "b\u00fcrgergarde": 1, "h\u00e4upter": 1, "wirthin": 1, "canzlei": 1, "finanzcollegiums": 1, "fenster": 1, "schwarzen": 1, "thor": 1, "s\u00e4ulen": 1, "fu\u00df": 3, "bewillkommnung": 1, "kinder": 1, "blumen": 1, "unfall": 1, "weise": 2, "entfernung": 1, "hoffnung": 1, "\u00fcbel": 1, "kaiser": 3, "k\u00f6nig": 2, "uhr": 4, "garden": 1, "mann": 1, "stadt": 3, "neumarkte": 1, "rest": 1, "infanterie": 1, "artillerie": 1, "lichtern": 1, "fenstern": 1, "haus": 1, "tempel": 1, "buchstaben": 1, "zuschauer": 1, "sch\u00e4rfe": 1, "augen": 1, "dinge": 1, "festone": 1, "empfangss\u00e4ulen": 1, "m\u00e4dchen": 1, "kleider": 1, "wind": 1, "f\u00fcrsten": 1, "hoheit": 2, "vorbereitungen": 1, "abreise": 1, "wirthen": 1, "aufnahme": 1, "vorsorge": 1, "ressource": 1, "vorsteher": 1, "wetter": 1, "tische": 2, "dom": 1, "geb\u00e4ude": 1, "jahrszahlen": 1, "mitte": 1, "jahrhunderts": 1, "au\u00dfen": 1, "basrelief": 1, "bau": 1, "merkw\u00fcrdigste": 1, "taufstein": 3, "sockel": 1, "gruppen": 1, "kindern": 1, "seitealles": 1, "haaren": 1, "seite": 5, "altar": 1, "schildhaltendes": 2, "tafelhaltendes": 1, "fortsetzung": 1, "hunde": 1, "vierte": 1, "kirche": 1, "mu\u00dfverzehrende": 1, "theilnahme": 1, "obstverzehrende": 1, "vorstellungen": 1, "seiten": 1, "figur": 1, "gedanke": 1, "kindheit": 1, "compositionen": 1, "stellungen": 1, "fig\u00fcrchen": 1, "zoll": 1, "zeichnung": 1, "flusse": 1, "gegend": 3, "schiffe": 1, "schiff": 3, "scheffel": 1, "pirnaischen": 1, "steine": 2, "steinen": 1, "pfeiler": 1, "schiffer": 1, "bogen": 2, "strom": 1, "elbufer": 1, "stunden": 1, "thonschiefer": 1, "stunde": 2, "artilleristen": 1, "notizen": 1, "h\u00f6he": 1, "sonnenstein": 2, "sonnenuntergang": 1, "scheibe": 1, "wiederschein": 1, "wasser": 1, "aussicht": 2, "k\u00f6nigstein": 1, "festung": 1, "schlo\u00df": 1, "irren": 1, "kranken": 1, "kosten": 1, "g\u00e4rten": 1, "arzte": 1, "l\u00fccke": 1, "capelle": 1, "h\u00f6henrauch": 1, "bergreihen": 1, "gartenhause": 1, "herr": 1, "ende": 1, "bl\u00e4tter": 1, "reisetagebuchs": 1, "zettelchen": 1, "kutscher": 2, "sorge": 1, "dienste": 1, "equipage": 1, "kriegsschauplatz": 1, "himmel": 1, "fl\u00fcchtigen": 1, "weite": 1, "gesch\u00e4ft": 1, "kastanien": 1, "park": 1, "wegen": 1, "leben": 1, "jahre": 1, "unterschied": 1, "pferde": 1, "geschirr": 1, "dienst": 1, "ehrlichkeit": 1, "briefe": 1, "vergn\u00fcgen": 1, "gott": 1, "f\u00fc\u00dfen": 1, "ungl\u00fcck": 1, "arbeit": 1, "statten": 1, "monat": 1, "professor": 1, "zuschrift": 1, "technologie": 1, "b\u00fccher": 1, "biographie": 1, "stelle": 1, "august": 2, "briefchen": 1, "stein": 1, "liebe": 1, "freunden": 1, "nachbarn": 1, "mandarinen": 1, "antrieb": 1, "tage": 1, "folgezeit": 1, "plan": 1, "erbprinzen": 1, "prinzen": 1, "m\u00e4hrchen": 1, "todtentanze": 1, "ballade": 1, "spa\u00df": 1, "geliebten": 1, "schwiegermutter": 1, "ziele": 1, "beharrlichkeit": 2, "negotiationen": 1, "bef\u00f6rderung": 1, "attestat": 1, "sinn": 1, "mutter": 1, "hausbesitzer": 1, "name": 1}