[{"text": "weise", "count": 0.3287979746107146}, {"text": "zeit", "count": 0.3287979746107146}, {"text": "alter", "count": 0.1643989873053573}, {"text": "arbeit", "count": 0.1643989873053573}, {"text": "august", "count": 0.1643989873053573}, {"text": "beobachtungen", "count": 0.1643989873053573}, {"text": "bezirk", "count": 0.1643989873053573}, {"text": "cultur", "count": 0.1643989873053573}, {"text": "dichtungsarten", "count": 0.1643989873053573}, {"text": "form", "count": 0.1643989873053573}, {"text": "frau", "count": 0.1643989873053573}, {"text": "geduld", "count": 0.1643989873053573}, {"text": "gegenst\u00e4nde", "count": 0.1643989873053573}, {"text": "genu\u00df", "count": 0.1643989873053573}, {"text": "gr\u00fc\u00dfen", "count": 0.1643989873053573}, {"text": "hoffnung", "count": 0.1643989873053573}, {"text": "ihrigen", "count": 0.1643989873053573}, {"text": "jahr", "count": 0.1643989873053573}, {"text": "kalender", "count": 0.1643989873053573}, {"text": "leben", "count": 0.1643989873053573}, {"text": "lieber", "count": 0.1643989873053573}, {"text": "nachspiel", "count": 0.1643989873053573}, {"text": "reise", "count": 0.1643989873053573}, {"text": "schatz", "count": 0.1643989873053573}, {"text": "seiten", "count": 0.1643989873053573}, {"text": "spa\u00df", "count": 0.1643989873053573}, {"text": "tagen", "count": 0.1643989873053573}, {"text": "vermischung", "count": 0.1643989873053573}, {"text": "vorspiel", "count": 0.1643989873053573}, {"text": "wege", "count": 0.1643989873053573}, {"text": "worte", "count": 0.1643989873053573}]