[{"text": "see", "count": 0.2945284162042896}, {"text": "leute", "count": 0.1963522774695264}, {"text": "staubbach", "count": 0.1963522774695264}, {"text": "wetter", "count": 0.1963522774695264}, {"text": "wolken", "count": 0.1963522774695264}, {"text": "gegend", "count": 0.1472642081021448}, {"text": "gipfel", "count": 0.1472642081021448}, {"text": "hand", "count": 0.1472642081021448}, {"text": "insel", "count": 0.1472642081021448}, {"text": "murten", "count": 0.1472642081021448}, {"text": "oktober", "count": 0.1472642081021448}, {"text": "sonne", "count": 0.1472642081021448}, {"text": "art", "count": 0.0981761387347632}, {"text": "berg", "count": 0.0981761387347632}, {"text": "berge", "count": 0.0981761387347632}, {"text": "beschreibung", "count": 0.0981761387347632}, {"text": "bieler", "count": 0.0981761387347632}, {"text": "bild", "count": 0.0981761387347632}, {"text": "brunnen", "count": 0.0981761387347632}, {"text": "gefahr", "count": 0.0981761387347632}, {"text": "gegenst\u00e4nde", "count": 0.0981761387347632}, {"text": "gletschern", "count": 0.0981761387347632}, {"text": "himmel", "count": 0.0981761387347632}, {"text": "lauterbrunnen", "count": 0.0981761387347632}, {"text": "luft", "count": 0.0981761387347632}, {"text": "mittag", "count": 0.0981761387347632}, {"text": "ort", "count": 0.0981761387347632}, {"text": "pracht", "count": 0.0981761387347632}, {"text": "regen", "count": 0.0981761387347632}, {"text": "reise", "count": 0.0981761387347632}, {"text": "schiff", "count": 0.0981761387347632}, {"text": "seite", "count": 0.0981761387347632}, {"text": "stadt", "count": 0.0981761387347632}, {"text": "stand", "count": 0.0981761387347632}, {"text": "thal", "count": 0.0981761387347632}, {"text": "weile", "count": 0.0981761387347632}, {"text": "zeit", "count": 0.0981761387347632}, {"text": "aar", "count": 0.0490880693673816}, {"text": "alpen", "count": 0.0490880693673816}, {"text": "annet", "count": 0.0490880693673816}, {"text": "anschein", "count": 0.0490880693673816}, {"text": "augen", "count": 0.0490880693673816}, {"text": "augenarzt", "count": 0.0490880693673816}, {"text": "augenblicke", "count": 0.0490880693673816}, {"text": "ausbruch", "count": 0.0490880693673816}, {"text": "aussicht", "count": 0.0490880693673816}, {"text": "be", "count": 0.0490880693673816}, {"text": "begriff", "count": 0.0490880693673816}, {"text": "beinhaus", "count": 0.0490880693673816}, {"text": "bekanndtschaft", "count": 0.0490880693673816}, {"text": "bilden", "count": 0.0490880693673816}, {"text": "bl\u00fcte", "count": 0.0490880693673816}, {"text": "bogen", "count": 0.0490880693673816}, {"text": "brief", "count": 0.0490880693673816}, {"text": "buche", "count": 0.0490880693673816}, {"text": "burgundern", "count": 0.0490880693673816}, {"text": "b\u00e4ren", "count": 0.0490880693673816}, {"text": "b\u00fcrger", "count": 0.0490880693673816}, {"text": "decoration", "count": 0.0490880693673816}, {"text": "despotismus", "count": 0.0490880693673816}, {"text": "dorf", "count": 0.0490880693673816}, {"text": "durchschnitt", "count": 0.0490880693673816}, {"text": "d\u00fcrre", "count": 0.0490880693673816}, {"text": "eindruk", "count": 0.0490880693673816}, {"text": "einf\u00e4lle", "count": 0.0490880693673816}, {"text": "eise", "count": 0.0490880693673816}, {"text": "ei\u00dfgebirge", "count": 0.0490880693673816}, {"text": "elend", "count": 0.0490880693673816}, {"text": "emmedingen", "count": 0.0490880693673816}, {"text": "erinnerung", "count": 0.0490880693673816}, {"text": "erscheinungen", "count": 0.0490880693673816}, {"text": "erz\u00e4hlung", "count": 0.0490880693673816}, {"text": "felsen", "count": 0.0490880693673816}, {"text": "felsens", "count": 0.0490880693673816}, {"text": "felsw\u00e4nden", "count": 0.0490880693673816}, {"text": "flecke", "count": 0.0490880693673816}, {"text": "fleisch", "count": 0.0490880693673816}, {"text": "flek", "count": 0.0490880693673816}, {"text": "forelle", "count": 0.0490880693673816}, {"text": "formen", "count": 0.0490880693673816}, {"text": "frau", "count": 0.0490880693673816}, {"text": "fr\u00fchst\u00fcck", "count": 0.0490880693673816}, {"text": "furcht", "count": 0.0490880693673816}, {"text": "geb\u00e4ude", "count": 0.0490880693673816}, {"text": "geb\u00e4uden", "count": 0.0490880693673816}, {"text": "gedancke", "count": 0.0490880693673816}, {"text": "gegenden", "count": 0.0490880693673816}, {"text": "gegenstand", "count": 0.0490880693673816}, {"text": "geist", "count": 0.0490880693673816}, {"text": "geister", "count": 0.0490880693673816}, {"text": "gelegenheit", "count": 0.0490880693673816}, {"text": "geleitsmann", "count": 0.0490880693673816}, {"text": "gesang", "count": 0.0490880693673816}, {"text": "gesange", "count": 0.0490880693673816}, {"text": "geschichte", "count": 0.0490880693673816}, {"text": "gesellschaffter", "count": 0.0490880693673816}, {"text": "gew\u00f6lk", "count": 0.0490880693673816}, {"text": "gleichheit", "count": 0.0490880693673816}, {"text": "gl\u00e4tscher", "count": 0.0490880693673816}, {"text": "gl\u00fcck", "count": 0.0490880693673816}, {"text": "grindelwald", "count": 0.0490880693673816}, {"text": "grus", "count": 0.0490880693673816}, {"text": "gr\u00f6sse", "count": 0.0490880693673816}, {"text": "gr\u00fcnde", "count": 0.0490880693673816}, {"text": "haupt", "count": 0.0490880693673816}, {"text": "hauptstrasse", "count": 0.0490880693673816}, {"text": "horngestalt", "count": 0.0490880693673816}, {"text": "hospital", "count": 0.0490880693673816}, {"text": "kirchhof", "count": 0.0490880693673816}, {"text": "knebeln", "count": 0.0490880693673816}, {"text": "kopf", "count": 0.0490880693673816}, {"text": "land", "count": 0.0490880693673816}, {"text": "landschaft", "count": 0.0490880693673816}, {"text": "landssprache", "count": 0.0490880693673816}, {"text": "laune", "count": 0.0490880693673816}, {"text": "leiterw\u00e4gelgen", "count": 0.0490880693673816}, {"text": "lichte", "count": 0.0490880693673816}, {"text": "lichtern", "count": 0.0490880693673816}, {"text": "lieblichkeit", "count": 0.0490880693673816}, {"text": "listen", "count": 0.0490880693673816}, {"text": "l\u00fccke", "count": 0.0490880693673816}, {"text": "menschen", "count": 0.0490880693673816}, {"text": "mitstreiter", "count": 0.0490880693673816}, {"text": "mittagsblik", "count": 0.0490880693673816}, {"text": "mittagsessens", "count": 0.0490880693673816}, {"text": "moor", "count": 0.0490880693673816}, {"text": "mythologie", "count": 0.0490880693673816}, {"text": "natur", "count": 0.0490880693673816}, {"text": "nebel", "count": 0.0490880693673816}, {"text": "neugier", "count": 0.0490880693673816}, {"text": "neust\u00e4dter", "count": 0.0490880693673816}, {"text": "obern", "count": 0.0490880693673816}, {"text": "oktbr", "count": 0.0490880693673816}, {"text": "orten", "count": 0.0490880693673816}, {"text": "papier", "count": 0.0490880693673816}, {"text": "perukenmacher", "count": 0.0490880693673816}, {"text": "pfarer", "count": 0.0490880693673816}, {"text": "pfarrer", "count": 0.0490880693673816}, {"text": "pfarrhause", "count": 0.0490880693673816}, {"text": "pfarrhauss", "count": 0.0490880693673816}, {"text": "pferde", "count": 0.0490880693673816}, {"text": "rathsschiffe", "count": 0.0490880693673816}, {"text": "reihe", "count": 0.0490880693673816}, {"text": "reinlichkeit", "count": 0.0490880693673816}, {"text": "reisebeschreibung", "count": 0.0490880693673816}, {"text": "religion", "count": 0.0490880693673816}, {"text": "ried", "count": 0.0490880693673816}, {"text": "schaffner", "count": 0.0490880693673816}, {"text": "schiffer", "count": 0.0490880693673816}, {"text": "schlacht", "count": 0.0490880693673816}, {"text": "schnee", "count": 0.0490880693673816}, {"text": "schwindel", "count": 0.0490880693673816}, {"text": "schwindels", "count": 0.0490880693673816}, {"text": "sch\u00f6nheit", "count": 0.0490880693673816}, {"text": "seele", "count": 0.0490880693673816}, {"text": "speck", "count": 0.0490880693673816}, {"text": "staats", "count": 0.0490880693673816}, {"text": "standpunckten", "count": 0.0490880693673816}, {"text": "stieg", "count": 0.0490880693673816}, {"text": "stiegelgen", "count": 0.0490880693673816}, {"text": "strophen", "count": 0.0490880693673816}, {"text": "st\u00fcckgen", "count": 0.0490880693673816}, {"text": "tag", "count": 0.0490880693673816}, {"text": "tagbuch", "count": 0.0490880693673816}, {"text": "tage", "count": 0.0490880693673816}, {"text": "tagebuch", "count": 0.0490880693673816}, {"text": "tags", "count": 0.0490880693673816}, {"text": "thaten", "count": 0.0490880693673816}, {"text": "tour", "count": 0.0490880693673816}, {"text": "uhr", "count": 0.0490880693673816}, {"text": "wagen", "count": 0.0490880693673816}, {"text": "wand", "count": 0.0490880693673816}, {"text": "wartensleben", "count": 0.0490880693673816}, {"text": "weeg", "count": 0.0490880693673816}, {"text": "weege", "count": 0.0490880693673816}, {"text": "wercke", "count": 0.0490880693673816}, {"text": "wirthschaft", "count": 0.0490880693673816}, {"text": "wirthshaus", "count": 0.0490880693673816}, {"text": "wirthsh\u00e4usser", "count": 0.0490880693673816}, {"text": "wohlbefinden", "count": 0.0490880693673816}, {"text": "wolck", "count": 0.0490880693673816}, {"text": "worten", "count": 0.0490880693673816}, {"text": "zettel", "count": 0.0490880693673816}, {"text": "zeugen", "count": 0.0490880693673816}, {"text": "zeughaus", "count": 0.0490880693673816}, {"text": "zingelgletscher", "count": 0.0490880693673816}, {"text": "zingelgletschers", "count": 0.0490880693673816}, {"text": "zingelhorn", "count": 0.0490880693673816}, {"text": "zweck", "count": 0.0490880693673816}]